reahlbalancesheet.py
ReahlBalanceSheet-0.0.1.dist-info/LICENSE
ReahlBalanceSheet-0.0.1.dist-info/METADATA
ReahlBalanceSheet-0.0.1.dist-info/WHEEL
ReahlBalanceSheet-0.0.1.dist-info/top_level.txt
ReahlBalanceSheet-0.0.1.dist-info/RECORD
