Metadata-Version: 2.1
Name: ReahlBalanceSheet
Version: 0.0.1
Summary: Create new, build and install Python Packages from a template
Author: Hendrik du Toit
Author-email: hendrik@brightedge.co.za
Classifier: Development Status :: 3 - Alpha
Classifier: Intended Audience :: Developers
Classifier: Topic :: Software Development
Classifier: Topic :: Software Development
Classifier: Topic :: Software Development :: Version Control
Classifier: Topic :: Software Development :: Version Control :: Git
Classifier: License :: OSI Approved :: MIT License
Classifier: Programming Language :: Python :: 3.8
License-File: LICENSE
Requires-Dist: reahl-component (<6.1,>=6.0)
Requires-Dist: reahl-web (<6.1,>=6.0)
Requires-Dist: reahl-sqlalchemysupport (<6.1,>=6.0)
Requires-Dist: reahl-sqlitesupport (<6.1,>=6.0)
Requires-Dist: reahl-web-declarative (<6.1,>=6.0)
